<?xml version="1.0" encoding="UTF-8" standalone="yes"?>
<Document xmlns="urn:iso:std:iso:20022:tech:xsd:pain.008.003.02" xmlns:xsi="http://www.w3.org/2001/XMLSchema-instance" xsi:schemaLocation="urn:iso:std:iso:20022:tech:xsd:pain.008.003.02 pain.008.003.02.xsd">
    <CstmrDrctDbtInitn>
        <GrpHdr>
            <MsgId>~EREIGNIS_R~</MsgId>
            <CreDtTm>~MOMENT~!Zeitstempel</CreDtTm>
            <NbOfTxs>~ANZAHL~</NbOfTxs>
            <CtrlSum>~SUMME~!Komma</CtrlSum>
            <InitgPty>
                <Nm>~Einreicher.Name~</Nm>
            </InitgPty>
        </GrpHdr>
        <PmtInf>
            <PmtInfId>PID0</PmtInfId>
            <PmtMtd>DD</PmtMtd>
            <BtchBookg>true</BtchBookg>
            <NbOfTxs>~ANZAHL~</NbOfTxs>
            <CtrlSum>~SUMME~!Komma</CtrlSum>
            <PmtTpInf>
                <SvcLvl>
                    <Cd>SEPA</Cd>
                </SvcLvl>
                <LclInstrm>
                    <Cd>COR1</Cd>
                </LclInstrm>
                <SeqTp>FRST</SeqTp>
            </PmtTpInf>
            <ReqdColltnDt>~AusfuehrungsDatum~!Datum</ReqdColltnDt>
            <Cdtr>
                <Nm>~Einreicher.Name~</Nm>
            </Cdtr>
            <CdtrAcct>
                <Id>
                    <IBAN>~Einreicher.IBAN~</IBAN>
                </Id>
            </CdtrAcct>
            <CdtrAgt>
                <FinInstnId>
                    <BIC>~Einreicher.BIC~</BIC>
                </FinInstnId>
            </CdtrAgt>
            <ChrgBr>SLEV</ChrgBr>
<!-- BEGIN POSTEN --> 
            <DrctDbtTxInf>
                <PmtId>
                    <EndToEndId>~EndeZuEndeReferenz~</EndToEndId>
                </PmtId>
                <InstdAmt Ccy="EUR">~Betrag~!Komma</InstdAmt>
                <DrctDbtTx>
                    <MndtRltdInf>
                        <MndtId>RID~RID~</MndtId>
                        <DtOfSgntr>~MandatsDatum~!Datum</DtOfSgntr>
                        <AmdmntInd>false</AmdmntInd>
                    </MndtRltdInf>
                    <CdtrSchmeId>
                        <Id>
                            <PrvtId>
                                <Othr>
                                    <Id>~Einreicher.ID~</Id>
                                    <SchmeNm>
                                        <Prtry>SEPA</Prtry>
                                    </SchmeNm>
                                </Othr>
                            </PrvtId>
                        </Id>
                    </CdtrSchmeId>
                </DrctDbtTx>
                <DbtrAgt>
                    <FinInstnId>
                        <BIC>~BIC~</BIC>
                    </FinInstnId>
                </DbtrAgt>
                <Dbtr>
                    <Nm>~Name~</Nm>
                </Dbtr>
                <DbtrAcct>
                    <Id>
                        <IBAN>~IBAN~</IBAN>
                    </Id>
                </DbtrAcct>
                <RmtInf>
                    <Ustrd>~VZ1~ ~VZ2~ ~VZ3~ ~VZ4~ ~VZ5~ ~VZ6~ ~VZ7~!^T</Ustrd>
                </RmtInf>
            </DrctDbtTxInf>
<!-- END POSTEN --> 
        </PmtInf>
    </CstmrDrctDbtInitn>
</Document>
